upt_cran/__init__.py
upt_cran/upt_cran.py
upt_cran/tests/__init__.py
upt_cran/tests/test_upt_cran.py
upt_cran-0.2.dist-info/LICENSE
upt_cran-0.2.dist-info/METADATA
upt_cran-0.2.dist-info/WHEEL
upt_cran-0.2.dist-info/entry_points.txt
upt_cran-0.2.dist-info/top_level.txt
upt_cran-0.2.dist-info/RECORD
